{"note":"This file is an internal implementation detail to speed up HTML report generation. Its format can change at any time. You might be looking for the JSON report: https://coverage.rtfd.io/cmd.html#cmd-json","format":5,"version":"7.11.0","globals":"7e05eb956e01b4ec0cb57888d8a2007e","files":{"calculator_py":{"hash":"973d274da47c47d6bd17041934ef9d39","index":{"url":"calculator_py.html","file":"calculator.py","description":"","nums":{"precision":0,"n_files":1,"n_statements":24,"n_excluded":0,"n_missing":0,"n_branches":0,"n_partial_branches":0,"n_missing_branches":0}}},"z_a44f0ac069e85531_test_calculator_py":{"hash":"e12bd04e2cf81311bdc3749d86220fb4","index":{"url":"z_a44f0ac069e85531_test_calculator_py.html","file":"tests\\test_calculator.py","description":"","nums":{"precision":0,"n_files":1,"n_statements":124,"n_excluded":0,"n_missing":9,"n_branches":0,"n_partial_branches":0,"n_missing_branches":0}}}}}